odoo/addons/web_widget_json_graph/README.rst
odoo/addons/web_widget_json_graph/__init__.py
odoo/addons/web_widget_json_graph/__manifest__.py
odoo/addons/web_widget_json_graph/i18n/ca.po
odoo/addons/web_widget_json_graph/i18n/es.po
odoo/addons/web_widget_json_graph/i18n/pt_BR.po
odoo/addons/web_widget_json_graph/i18n/web_widget_json_graph.pot
odoo/addons/web_widget_json_graph/readme/CONTRIBUTORS.rst
odoo/addons/web_widget_json_graph/readme/CREDITS.rst
odoo/addons/web_widget_json_graph/readme/DESCRIPTION.rst
odoo/addons/web_widget_json_graph/readme/ROADMAP.rst
odoo/addons/web_widget_json_graph/readme/USAGE.rst
odoo/addons/web_widget_json_graph/static/data.tsv
odoo/addons/web_widget_json_graph/static/description/icon.png
odoo/addons/web_widget_json_graph/static/description/index.html
odoo/addons/web_widget_json_graph/static/description/widget_in_action.png
odoo/addons/web_widget_json_graph/static/src/js/web_widget_json_graph.js
odoo/addons/web_widget_json_graph/static/src/scss/web_widget_json_graph.scss
odoo/addons/web_widget_json_graph/static/src/xml/web_widget_json_graph.xml
odoo/addons/web_widget_json_graph/views/assets.xml
odoo12_addon_web_widget_json_graph-12.0.1.0.0.99.dev7.dist-info/METADATA
odoo12_addon_web_widget_json_graph-12.0.1.0.0.99.dev7.dist-info/WHEEL
odoo12_addon_web_widget_json_graph-12.0.1.0.0.99.dev7.dist-info/top_level.txt
odoo12_addon_web_widget_json_graph-12.0.1.0.0.99.dev7.dist-info/RECORD
